neon_utils/__init__.py
neon_utils/authentication_utils.py
neon_utils/cache_utils.py
neon_utils/configuration_utils.py
neon_utils/decorators.py
neon_utils/file_utils.py
neon_utils/hana_utils.py
neon_utils/language_utils.py
neon_utils/location_utils.py
neon_utils/log_utils.py
neon_utils/logger.py
neon_utils/message_utils.py
neon_utils/messagebus_utils.py
neon_utils/metrics_utils.py
neon_utils/mq_utils.py
neon_utils/net_utils.py
neon_utils/packaging_utils.py
neon_utils/parse_utils.py
neon_utils/process_utils.py
neon_utils/search_utils.py
neon_utils/signal_utils.py
neon_utils/skill_utils.py
neon_utils/socket_utils.py
neon_utils/user_utils.py
neon_utils/validator_utils.py
neon_utils/web_utils.py
neon_utils/default_configurations/__init__.py
neon_utils/default_configurations/default_user_conf.yml
neon_utils/log_aggregators/__init__.py
neon_utils/log_aggregators/sentry.py
neon_utils/res/snd/acknowledge.mp3
neon_utils/res/snd/loaded.wav
neon_utils/res/snd/start_listening.wav
neon_utils/res/text/en-us/neon.voc
neon_utils/res/text/en-us/no.voc
neon_utils/res/text/en-us/stop.voc
neon_utils/res/text/en-us/yes.voc
neon_utils/res/ui/neon_logo.png
neon_utils/skills/__init__.py
neon_utils/skills/common_message_skill.py
neon_utils/skills/common_play_skill.py
neon_utils/skills/common_query_skill.py
neon_utils/skills/instructor_skill.py
neon_utils/skills/kiosk_skill.py
neon_utils/skills/mycroft_skill.py
neon_utils/skills/neon_fallback_skill.py
neon_utils/skills/neon_skill.py
neon_utils/skills/skill_gui.py
tests/__init__.py
tests/authentication_util_tests.py
tests/cache_util_tests.py
tests/configuration_util_tests.py
tests/file_util_tests.py
tests/hana_util_tests.py
tests/language_util_tests.py
tests/location_util_tests.py
tests/log_util_tests.py
tests/message_util_tests.py
tests/messagebus_util_tests.py
tests/metric_util_tests.py
tests/mq_util_tests.py
tests/neon_skill_tests.py
tests/net_util_tests.py
tests/packaging_util_tests.py
tests/parse_util_tests.py
tests/search_util_tests.py
neon_utils-1.14.0.dist-info/LICENSE.md
neon_utils-1.14.0.dist-info/METADATA
neon_utils-1.14.0.dist-info/WHEEL
neon_utils-1.14.0.dist-info/entry_points.txt
neon_utils-1.14.0.dist-info/top_level.txt
neon_utils-1.14.0.dist-info/RECORD
