Metadata-Version: 2.1
Name: neon-utils
Version: 1.14.0
Summary: Utilities for NeonAI
Home-page: https://github.com/neongeckocom/neon-skill-utils
Author: Neongecko
Author-email: developers@neon.ai
License: BSD-3-Clause
Classifier: Programming Language :: Python :: 3
Classifier: Operating System :: OS Independent
Requires-Python: >=3.6
License-File: LICENSE.md
Requires-Dist: ovos-bus-client>=0.0.3,~=0.0
Requires-Dist: combo-lock~=0.2
Requires-Dist: pytz>=2022.1
Requires-Dist: timezonefinder~=5.2
Requires-Dist: nltk~=3.5
Requires-Dist: pyyaml<7.0,>=5.4
Requires-Dist: ovos-lingua-franca~=0.4
Requires-Dist: ovos-utils>=0.0.35,~=0.0
Requires-Dist: geopy~=2.1
Requires-Dist: ovos-config>=0.0.9,~=0.0
Requires-Dist: ovos-workshop>=0.0.15,~=0.0
Provides-Extra: audio
Requires-Dist: soundfile~=0.10; extra == "audio"
Requires-Dist: librosa<0.10,~=0.8; extra == "audio"
Requires-Dist: pydub~=0.25; extra == "audio"
Provides-Extra: configuration
Requires-Dist: ruamel.yaml~=0.16; extra == "configuration"
Provides-Extra: network
Requires-Dist: requests; extra == "network"
Requires-Dist: beautifulsoup4~=4.9; extra == "network"
Requires-Dist: lxml~=4.5; extra == "network"
Requires-Dist: netifaces~=0.10; extra == "network"
Requires-Dist: neon-mq-connector>=0.5.1,~=0.2; extra == "network"
Provides-Extra: sentry
Requires-Dist: sentry-sdk; extra == "sentry"
Provides-Extra: signal
Requires-Dist: mock; extra == "signal"
Provides-Extra: skills
Requires-Dist: mock; extra == "skills"
Requires-Dist: toml~=0.10; extra == "skills"
Provides-Extra: test
Requires-Dist: pytest; extra == "test"
Requires-Dist: pytest-timeout; extra == "test"
Requires-Dist: pytest-cov; extra == "test"
Requires-Dist: mock; extra == "test"
Requires-Dist: ovos-plugin-manager~=0.1; extra == "test"
Requires-Dist: neon-lang-plugin-libretranslate; extra == "test"
